superduper_sentence_transformers/__init__.py
superduper_sentence_transformers/model.py
superduper_sentence_transformers-0.10.0.dist-info/licenses/LICENSE
superduper_sentence_transformers-0.10.0.dist-info/METADATA
superduper_sentence_transformers-0.10.0.dist-info/WHEEL
superduper_sentence_transformers-0.10.0.dist-info/top_level.txt
superduper_sentence_transformers-0.10.0.dist-info/RECORD
