Metadata-Version: 2.4
Name: superduper_sentence_transformers
Version: 0.10.0
Summary: superduper allows users to work with self-hosted embedding models via [Sentence-Transformers](https://sbert.net).
Maintainer-email: "superduper.io, Inc." <opensource@superduper.io>
License: 
Project-URL: homepage, https://superduper.io
Project-URL: documentation, https://docs.superduper.io/docs/intro
Project-URL: source, https://github.com/superduper-io/superduper
Keywords: databases,mongodb,data-science,machine-learning,mlops,vector-database,ai
Requires-Python: >=3.10
License-File: LICENSE
Requires-Dist: sentence-transformers>=2.2.2
Dynamic: license-file
